LICENSE.txt
MANIFEST.in
README.rst
requirements.txt
setup.cfg
setup.py
doc/Makefile
doc/conf.py
doc/index.rst
doc/objects.inv
doc/rst/install.rst
doc/rst/module.rst
doc/rst/refman.rst
doc/rst/tutor.rst
doc/rst/install/extensions.rst
doc/rst/install/ext/client.rst
doc/rst/module/extensions.rst
doc/rst/module/ext/client/client.rst
doc/rst/module/ext/client/core.rst
doc/rst/module/ext/client/plugins.rst
doc/rst/module/ext/client/core/autocompleter.rst
doc/rst/module/ext/client/core/colorizer.rst
doc/rst/module/ext/client/core/config.rst
doc/rst/module/ext/client/core/editor.rst
doc/rst/module/ext/client/core/explorer.rst
doc/rst/module/ext/client/core/filetab.rst
doc/rst/module/ext/client/core/formatter.rst
doc/rst/module/ext/client/core/gui.rst
doc/rst/module/ext/client/core/help.rst
doc/rst/module/ext/client/core/logger.rst
doc/rst/module/ext/client/core/notebook.rst
doc/rst/module/ext/client/core/plugin.rst
doc/rst/module/ext/client/core/pluginmanager.rst
doc/rst/module/ext/client/core/tkimport.rst
doc/rst/module/ext/client/core/tooltip.rst
doc/rst/module/ext/client/core/translator.rst
doc/rst/module/ext/client/core/utils.rst
doc/rst/module/ext/client/core/yoda_tree.rst
doc/rst/module/ext/client/plugins/gitclient.rst
doc/rst/module/ext/client/plugins/syntaxchecker.rst
doc/rst/refman/ext/client.rst
doc/rst/tutor/extensions.rst
doc/rst/tutor/ext/client/client.rst
doc/rst/tutor/ext/client/tut1_explorer.rst
doc/rst/tutor/ext/client/tut2_editor.rst
doc/rst/tutor/ext/client/tut3_yoda_tree.rst
doc/rst/tutor/ext/client/tut4_plugins.rst
doc/rst/tutor/ext/client/tut5_gitclient.rst
doc/rst/tutor/ext/client/fig/editor_01_goto.png
doc/rst/tutor/ext/client/fig/editor_02_goto.png
doc/rst/tutor/ext/client/fig/editor_03_find.png
doc/rst/tutor/ext/client/fig/editor_04_find.png
doc/rst/tutor/ext/client/fig/editor_05_replace.png
doc/rst/tutor/ext/client/fig/editor_06_replace.png
doc/rst/tutor/ext/client/fig/editor_07_syntax_highlighter.png
src/hydratk_client.egg-info/PKG-INFO
src/hydratk_client.egg-info/SOURCES.txt
src/hydratk_client.egg-info/dependency_links.txt
src/hydratk_client.egg-info/entry_points.txt
src/hydratk_client.egg-info/not-zip-safe
src/hydratk_client.egg-info/requires.txt
src/hydratk_client.egg-info/top_level.txt
